machine_learning_data_pipeline-1.0.3.dist-info/METADATA
machine_learning_data_pipeline-1.0.3.dist-info/RECORD
machine_learning_data_pipeline-1.0.3.dist-info/WHEEL
machine_learning_data_pipeline-1.0.3.dist-info/top_level.txt
mldp/__init__.py
mldp/pipeline.py
mldp/steps/__init__.py
mldp/steps/base_step.py
mldp/steps/formatters/__init__.py
mldp/steps/formatters/base_formatter.py
mldp/steps/formatters/pandas_formatter.py
mldp/steps/general/__init__.py
mldp/steps/general/chunk_size_adjuster.py
mldp/steps/preprocessing/__init__.py
mldp/steps/preprocessing/base_preprocessor.py
mldp/steps/preprocessing/file_downloader.py
mldp/steps/readers/__init__.py
mldp/steps/readers/base_reader.py
mldp/steps/readers/common.py
mldp/steps/readers/csv_reader.py
mldp/steps/transformers/__init__.py
mldp/steps/transformers/base_transformer.py
mldp/steps/transformers/common.py
mldp/steps/transformers/fields_selector.py
mldp/steps/transformers/function_applier.py
mldp/steps/transformers/padder.py
mldp/steps/transformers/shuffler.py
mldp/steps/transformers/token_processor.py
mldp/steps/transformers/vocab_mapper.py
mldp/steps/transformers/window_slider.py
mldp/tests/__init__.py
mldp/tests/common.py
mldp/tests/test_chunk_size_adjuster.py
mldp/tests/test_data_pipeline_integration.py
mldp/tests/test_readers.py
mldp/tests/test_transformers.py
mldp/tests/test_tutorials.py
mldp/tests/test_validation_utils.py
mldp/tests/test_vocabulary_util.py
mldp/utils/__init__.py
mldp/utils/constants.py
mldp/utils/util_classes/__init__.py
mldp/utils/util_classes/fs_accessor_factory.py
mldp/utils/util_classes/ordered_attrs.py
mldp/utils/util_classes/vocabulary.py
mldp/utils/util_classes/fs_accessors/__init__.py
mldp/utils/util_classes/fs_accessors/base_fs_accessor.py
mldp/utils/util_classes/fs_accessors/local_fs_accessor.py
mldp/utils/util_classes/fs_accessors/s3_fs_accessor.py
mldp/utils/util_funcs/__init__.py
mldp/utils/util_funcs/aws.py
mldp/utils/util_funcs/data_chunks.py
mldp/utils/util_funcs/formatting.py
mldp/utils/util_funcs/general.py
mldp/utils/util_funcs/logging_utils.py
mldp/utils/util_funcs/multi_processing.py
mldp/utils/util_funcs/paths_and_files.py
