Metadata-Version: 2.1
Name: machine-learning-data-pipeline
Version: 1.0.3
Summary: Pipeline module for parallel real-time data processing for machine learning models development and production purposes.
Home-page: https://github.com/ixlan/machine-learning-data-pipeline
Author: Arthur Brazinskas
Author-email: bulletdll@gmail.com
License: UNKNOWN
Platform: UNKNOWN
Requires-Dist: numpy (==1.15.2)
Requires-Dist: pandas (==0.21.1)
Requires-Dist: plumbum (==1.6.7)
Requires-Dist: s3fs (==0.1.6)
Requires-Dist: urllib3 (==1.23)
Requires-Dist: mock (==2.0.0)
